oxidize/__init__.py
oxidize-0.7.0.dist-info/METADATA
oxidize-0.7.0.dist-info/WHEEL
oxidize-0.7.0.dist-info/top_level.txt
oxidize-0.7.0.dist-info/RECORD
