Metadata-Version: 2.4
Name: oxidize
Version: 0.7.0
Summary: High-performance data processing tools for Python, built with Rust
Author: Eric Aleman
Project-URL: Repository, https://github.com/ericaleman/oxidize
Keywords: data-processing,rust,performance,tools
Classifier: Development Status :: 4 - Beta
Classifier: Intended Audience :: Developers
Classifier: Programming Language :: Python :: 3
Classifier: Programming Language :: Python :: 3.9
Classifier: Programming Language :: Python :: 3.10
Classifier: Programming Language :: Python :: 3.11
Classifier: Programming Language :: Python :: 3.12
Classifier: Topic :: Software Development :: Libraries :: Python Modules
Classifier: Topic :: Text Processing
Requires-Python: >=3.9
